[
    
        {
            "src" : "/images/Learning/coinJar.png",
            "heading" : "Save money, the right way",
            "content": "Torem ipsum dolor sit amet, consectetur adipiscing elit. Nunc vulputate libero et velit interdum, ac aliquet odio mattis.",
            "Date" : "24 May 2023",
            "link": "Read Now"
        },
        {
            "src" : "/images/Learning/Goldcoins.png",
            "heading" : "Save money, the right way. Second line test",
            "content": "Torem ipsum dolor sit amet, consectetur adipiscing elit. Nunc vulputate libero et velit interdum, ac aliquet odio mattis.",
            "Date" : "24 May 2023",
            "link": "Read Now"
        },
        {
            "src" : "/images/Learning/NoteMoney.png",
            "heading" : "Save money, the right way. Second line test",
            "content": "Torem ipsum dolor sit amet, consectetur adipiscing elit. Nunc vulputate libero et velit interdum, ac aliquet odio mattis.",
            "Date" : "24 May 2023",
            "link": "Read Now"
        },
        {
            "src" : "/images/Learning/coinJar.png",
            "heading" : "Save money, the right way",
            "content": "Torem ipsum dolor sit amet, consectetur adipiscing elit. Nunc vulputate libero et velit interdum, ac aliquet odio mattis.",
            "Date" : "24 May 2023",
            "link": "Read Now"
        }
    
    
]